envcontrolz/__init__.py
envcontrolz-0.1.1.dist-info/METADATA
envcontrolz-0.1.1.dist-info/WHEEL
envcontrolz-0.1.1.dist-info/top_level.txt
envcontrolz-0.1.1.dist-info/RECORD
