Metadata-Version: 2.4
Name: envcontrolz
Version: 0.1.1
Summary: 知识
Requires-Python: >=3.10
